send_s3-3.1.0.dist-info/METADATA
send_s3-3.1.0.dist-info/WHEEL
send_s3-3.1.0.dist-info/entry_points.txt
send_s3-3.1.0.dist-info/licenses/LICENSE
send_s3/__init__.py
send_s3/actions/__init__.py
send_s3/actions/init.py
send_s3/actions/log.py
send_s3/actions/upload.py
send_s3/common.py
send_s3/config.py
send_s3/config.toml
send_s3/db.py
send_s3/s3.py
send_s3/schema.sql
send_s3-3.1.0.dist-info/RECORD
