Metadata-Version: 2.1
Name: send-s3
Version: 3.1.0
Summary: CLI tool for uploading files to S3-compatible storage services.
Keywords: uploader,s3,s3-compatible,cli
Home-page: https://github.com/baobao1270/send-s3
Author-Email: Joseph Chris <joseph@josephcz.xyz>
License: MIT
Project-URL: Homepage, https://github.com/baobao1270/send-s3
Project-URL: Repository, https://github.com/baobao1270/send-s3.git
Project-URL: Changelog, https://github.com/baobao1270/send-s3/blob/main/CHANGELOG.md
Project-URL: Documentation, https://github.com/baobao1270/send-s3/blob/main/README.md
Requires-Python: <4.0,>=3.11
Requires-Dist: pydantic-settings>=2.3.1
Requires-Dist: toml>=0.10.2
Requires-Dist: requests>=2.32.3
